approck_events_sdk/__init__.py
approck_events_sdk/_queue.py
approck_events_sdk/api.py
approck_events_sdk/client.py
approck_events_sdk/consts.py
approck_events_sdk/event.py
approck_events_sdk/hub.py
approck_events_sdk/minimal.py
approck_events_sdk/transport.py
approck_events_sdk/utils.py
approck_events_sdk-0.1.6.dist-info/METADATA
approck_events_sdk-0.1.6.dist-info/WHEEL
approck_events_sdk-0.1.6.dist-info/RECORD
