Metadata-Version: 2.1
Name: approck-events-sdk
Version: 0.1.6
Summary: 
Author: Aleksey Dalekin
Author-email: adalekin@gmail.com
Requires-Python: >=3.10,<4.0
Classifier: Programming Language :: Python :: 3
Classifier: Programming Language :: Python :: 3.10
Classifier: Programming Language :: Python :: 3.11
Classifier: Programming Language :: Python :: 3.12
Requires-Dist: certifi (>=2024.2.2,<2025.0.0)
Requires-Dist: urllib3 (>=1.25.4,<1.27)
